console_progressbar/__init__.py
console_progressbar/progressbar.py
console_progressbar-1.0.2.dist-info/DESCRIPTION.rst
console_progressbar-1.0.2.dist-info/METADATA
console_progressbar-1.0.2.dist-info/RECORD
console_progressbar-1.0.2.dist-info/WHEEL
console_progressbar-1.0.2.dist-info/metadata.json
console_progressbar-1.0.2.dist-info/top_level.txt
