Metadata-Version: 2.0
Name: console-progressbar
Version: 1.0.2
Summary: A simple progress bar for console
Home-page: https://github.com/bozoh/console_progressbar
Author: Carlos Alexandre S. da Fonseca
Author-email: carlos.alexandre@outlook.com
License: MIT
Keywords: progressbar console
Platform: UNKNOWN
Classifier: Development Status :: 5 - Production/Stable
Classifier: Environment :: Console
Classifier: Intended Audience :: Developers
Classifier: License :: OSI Approved :: MIT License
Classifier: Natural Language :: English
Classifier: Operating System :: OS Independent
Classifier: Programming Language :: Python :: 3.5
Classifier: Programming Language :: Python :: 3.6
Classifier: Topic :: Utilities
Requires-Python: >=3.5
Provides-Extra: dev
Requires-Dist: check-manifest; extra == 'dev'
Provides-Extra: test
Requires-Dist: coverage; extra == 'test'
